{"kind": "youtube#commentThreadListResponse", "etag": "Kcq-Jk4m7Pr1bHvP2k_nupyhOQc", "pageInfo": {"totalResults": 1, "resultsPerPage": 20}, "items": [{"kind": "youtube#commentThread", "etag": "6g70WlDp1j08SN3IyRZahlJXc8M", "id": "UgyQV5sX2ZC6k_TLqHp4AaABAg", "snippet": {"videoId": "FJmjGoV2ThU", "topLevelComment": {"kind": "youtube#comment", "etag": "_im4G01G8A4FU_E-iww4pDP1dbw", "id": "UgyQV5sX2ZC6k_TLqHp4AaABAg", "snippet": {"videoId": "FJmjGoV2ThU", "textDisplay": "Good Job and Support !   Bravo to China Rise Peacefully and be Strong !", "textOriginal": "Good Job and Support !   Bravo to China Rise Peacefully and be Strong !", "authorDisplayName": "Wella Wong", "authorProfileImageUrl": "https://yt3.ggpht.com/ytc/AKedOLT5NLfL2fdTmJKUaHDyQTeMg6fbg6uq--FHMA=s48-c-k-c0x00ffffff-no-rj", "authorChannelUrl": "http://www.youtube.com/channel/UC-KACc87Mh8TCdFZafnXMwA", "authorChannelId": {"value": "UC-KACc87Mh8TCdFZafnXMwA"}, "canRate": true, "viewerRating": "none", "likeCount": 0, "publishedAt": "2022-02-02T04:59:44Z", "updatedAt": "2022-02-02T04:59:44Z"}}, "canReply": true, "totalReplyCount": 0, "isPublic": true}}]}