{"kind": "youtube#commentThreadListResponse", "etag": "s9jbl7TUuNe1vAZLUhxVOtLBO3Y", "pageInfo": {"totalResults": 1, "resultsPerPage": 20}, "items": [{"kind": "youtube#commentThread", "etag": "0Mx_6se27xb3l7toQlg7c9afSG4", "id": "UgyMk7FqeFg8TgymKwZ4AaABAg", "snippet": {"videoId": "JpZnTcms4rE", "topLevelComment": {"kind": "youtube#comment", "etag": "zku7TL0lcR1kCb7IqF9ROlERuLo", "id": "UgyMk7FqeFg8TgymKwZ4AaABAg", "snippet": {"videoId": "JpZnTcms4rE", "textDisplay": "\ud83d\udc89\ud83e\udd26\ud83c\udffd\u200d\u2642\ufe0f\ud83d\udc6f\u200d\u2642\ufe0f\ud83d\udd4c\ud83d\udc80", "textOriginal": "\ud83d\udc89\ud83e\udd26\ud83c\udffd\u200d\u2642\ufe0f\ud83d\udc6f\u200d\u2642\ufe0f\ud83d\udd4c\ud83d\udc80", "authorDisplayName": "Rein Deer \ud83e\udd8c", "authorProfileImageUrl": "https://yt3.ggpht.com/mnKa8lZO3GyeeOPqB7ylOruY5SbpTAOed7JizMHUKkUd3j52sC_AriwQvBb5T4TKXy3hqWQA=s48-c-k-c0x00ffffff-no-rj", "authorChannelUrl": "http://www.youtube.com/channel/UCqXpfAj4PTYTrhCvwnAvYOA", "authorChannelId": {"value": "UCqXpfAj4PTYTrhCvwnAvYOA"}, "canRate": true, "viewerRating": "none", "likeCount": 0, "publishedAt": "2022-01-01T10:54:28Z", "updatedAt": "2022-01-01T10:54:28Z"}}, "canReply": true, "totalReplyCount": 0, "isPublic": true}}]}