{"kind": "youtube#commentThreadListResponse", "etag": "RnSmEm3y54ujGB37tcC-wq4uaII", "nextPageToken": "QURTSl9pMGl5UEU3VVZoWHpMMUp6NFhDRV9Nc2hlU245Z0QyaDc4T1k4RmlVTHlWMnlSX1U3VWVOSGNkVUEwQnFnTEtLUVBnWUVtNFhNYw==", "pageInfo": {"totalResults": 19, "resultsPerPage": 20}, "items": [{"kind": "youtube#commentThread", "etag": "KTJNlGQvNqXOQ77yBPNe4Su2vxg", "id": "UgzJtc2ytBpb2r0auRx4AaABAg", "snippet": {"videoId": "8A6esi1YcP0", "topLevelComment": {"kind": "youtube#comment", "etag": "ZCzxuxrcwvuLeekhb4A-TCetYqc", "id": "UgzJtc2ytBpb2r0auRx4AaABAg", "snippet": {"videoId": "8A6esi1YcP0", "textDisplay": "\u4e2d\u56fd\u4e16\u754c\u7b2c\u4e00\uff0c\u6b27\u7f8e\u81e3\u670d\uff0c\u4e07\u56fd\u6765\u671d\uff0c\u597d\u597d\u597d\u3002", "textOriginal": "\u4e2d\u56fd\u4e16\u754c\u7b2c\u4e00\uff0c\u6b27\u7f8e\u81e3\u670d\uff0c\u4e07\u56fd\u6765\u671d\uff0c\u597d\u597d\u597d\u3002", "authorDisplayName": "\u53e4\u5fb7\u66fc", "authorProfileImageUrl": "https://yt3.ggpht.com/ytc/AKedOLQg1sa3oVnCNcFTQUQPCiJ6aZr--4Caeu-XwOBQ=s48-c-k-c0x00ffffff-no-rj", "authorChannelUrl": "http://www.youtube.com/channel/UC85BPHzsQ3J1eseSgccj-Bg", "authorChannelId": {"value": "UC85BPHzsQ3J1eseSgccj-Bg"}, "canRate": true, "viewerRating": "none", "likeCount": 0, "publishedAt": "2022-02-15T22:58:09Z", "updatedAt": "2022-02-15T22:58:09Z"}}, "canReply": true, "totalReplyCount": 0, "isPublic": true}}, {"kind": "youtube#commentThread", "etag": "mxlNkcu8YmCNf4o3HoeDAVM3Qwc", "id": "Ugyy-1FEzDbUCcrBLvh4AaABAg", "snippet": {"videoId": "8A6esi1YcP0", "topLevelComment": {"kind": "youtube#comment", "etag": "27niICkXxj9jdobYyeZNwOtpxQU", "id": "Ugyy-1FEzDbUCcrBLvh4AaABAg", "snippet": {"videoId": "8A6esi1YcP0", "textDisplay": "\u56e0\u4e3a\u4f60\u662f\u7741\u773c\u778e\uff0c\u6240\u4ee5\u4e0d\u4e00\u6837\u3002", "textOriginal": "\u56e0\u4e3a\u4f60\u662f\u7741\u773c\u778e\uff0c\u6240\u4ee5\u4e0d\u4e00\u6837\u3002", "authorDisplayName": "zhibing005 li", "authorProfileImageUrl": "https://yt3.ggpht.com/ytc/AKedOLSILuv7yg2QaObL07OFf_qOH4GXRxBRXNfRqrbMKYRPk24AsSNPqrWU4rSF6QEz=s48-c-k-c0x00ffffff-no-rj", "authorChannelUrl": "http://www.youtube.com/channel/UCSzUu2hbiPzX6Yv0-ke35RQ", "authorChannelId": {"value": "UCSzUu2hbiPzX6Yv0-ke35RQ"}, "canRate": true, "viewerRating": "none", "likeCount": 0, "publishedAt": "2022-02-15T00:38:25Z", "updatedAt": "2022-02-15T00:38:25Z"}}, "canReply": true, "totalReplyCount": 0, "isPublic": true}}, {"kind": "youtube#commentThread", "etag": "g8MlzoJuIVXCTrBkY8Dov_q_uH0", "id": "UgzfRo8UBY9PnBO9rHt4AaABAg", "snippet": {"videoId": "8A6esi1YcP0", "topLevelComment": {"kind": "youtube#comment", "etag": "7j4IvCX0gmKlT5AX7aeXA-xZpys", "id": "UgzfRo8UBY9PnBO9rHt4AaABAg", "snippet": {"videoId": "8A6esi1YcP0", "textDisplay": "\u73b0\u573a\uff1a\u51ac\u5965\u6751\u7206\u4e25\u91cd\u6f0f\u6c34\uff0c\u503e\u76c6\u5982\u6c34\u5e18\u6d1e\uff01\u82ac\u5170\u9009\u624b\u6c42\u6551\uff1b\u5965\u59d4\u4f1a\u7f51\u8c37\u7231\u51cc\u5b98\u65b9\u8d44\u6599\u53d8\u52a8\uff1a\u5220\u9664\u653e\u5f03\u7f8e\u56fd\u7c4d\uff1b\u5238\u5546\u770b\u8dcc\u5b81\u5fb7\u8def\u6f14\u4f1a\u4e34\u65f6\u53d6\u6d88\uff01\u770b\u7a7a\u7814\u62a5\u7a81\u7136\u5220\u9664\uff1b\u6b63\u8363\u5730\u4ea7\u80a1\u503a\u95ea\u5d29\uff01\u80a1\u4ef7\u4e00\u5ea6\u8dcc\u8d8580%\uff1b\u6e2f\u5e9c\u4ee3\u8868\u56e2\u8d74\u6df1\u5733\u6c42\u63f4", "textOriginal": "\u73b0\u573a\uff1a\u51ac\u5965\u6751\u7206\u4e25\u91cd\u6f0f\u6c34\uff0c\u503e\u76c6\u5982\u6c34\u5e18\u6d1e\uff01\u82ac\u5170\u9009\u624b\u6c42\u6551\uff1b\u5965\u59d4\u4f1a\u7f51\u8c37\u7231\u51cc\u5b98\u65b9\u8d44\u6599\u53d8\u52a8\uff1a\u5220\u9664\u653e\u5f03\u7f8e\u56fd\u7c4d\uff1b\u5238\u5546\u770b\u8dcc\u5b81\u5fb7\u8def\u6f14\u4f1a\u4e34\u65f6\u53d6\u6d88\uff01\u770b\u7a7a\u7814\u62a5\u7a81\u7136\u5220\u9664\uff1b\u6b63\u8363\u5730\u4ea7\u80a1\u503a\u95ea\u5d29\uff01\u80a1\u4ef7\u4e00\u5ea6\u8dcc\u8d8580%\uff1b\u6e2f\u5e9c\u4ee3\u8868\u56e2\u8d74\u6df1\u5733\u6c42\u63f4", "authorDisplayName": "water85982", "authorProfileImageUrl": "https://yt3.ggpht.com/ytc/AKedOLRTSIMo7eAE4DoNP3qy20BE47BGRl5bumkoFg=s48-c-k-c0x00ffffff-no-rj", "authorChannelUrl": "http://www.youtube.com/channel/UClFZ1wKJZecGcDVZ2x4IKsA", "authorChannelId": {"value": "UClFZ1wKJZecGcDVZ2x4IKsA"}, "canRate": true, "viewerRating": "none", "likeCount": 0, "publishedAt": "2022-02-14T14:43:07Z", "updatedAt": "2022-02-14T14:43:07Z"}}, "canReply": true, "totalReplyCount": 0, "isPublic": true}}, {"kind": "youtube#commentThread", "etag": "i4_3wl1hbn9yQxBa32kNqQngyW0", "id": "Ugx3weaBiP0mMJLDy054AaABAg", "snippet": {"videoId": "8A6esi1YcP0", "topLevelComment": {"kind": "youtube#comment", "etag": "iPvLsZO85Mg5nD2RdNYVl9m_7q0", "id": "Ugx3weaBiP0mMJLDy054AaABAg", "snippet": {"videoId": "8A6esi1YcP0", "textDisplay": "\u770b\u89c6\u9891\u91cc\u5403\u7684\u90fd\u633a\u597d\u7684\u5440\uff0c\u6ce1\u83dc\u56fd\u7684\u8fd0\u52a8\u5458\u5728\u62b1\u6028\u4ec0\u4e48\u5440", "textOriginal": "\u770b\u89c6\u9891\u91cc\u5403\u7684\u90fd\u633a\u597d\u7684\u5440\uff0c\u6ce1\u83dc\u56fd\u7684\u8fd0\u52a8\u5458\u5728\u62b1\u6028\u4ec0\u4e48\u5440", "authorDisplayName": "TTing Yang", "authorProfileImageUrl": "https://yt3.ggpht.com/ytc/AKedOLQ5IzWol1IZUBlMuxhHhNVSR-JGWULLWCTHdw=s48-c-k-c0x00ffffff-no-rj", "authorChannelUrl": "http://www.youtube.com/channel/UCpsXvCYoZezDRxchXgMKbCw", "authorChannelId": {"value": "UCpsXvCYoZezDRxchXgMKbCw"}, "canRate": true, "viewerRating": "none", "likeCount": 0, "publishedAt": "2022-02-14T04:39:13Z", "updatedAt": "2022-02-14T04:39:13Z"}}, "canReply": true, "totalReplyCount": 1, "isPublic": true}, "replies": {"comments": [{"kind": "youtube#comment", "etag": "LWm-JN65bGiIs4Qt7FKfD3jl-6Q", "id": "Ugx3weaBiP0mMJLDy054AaABAg.9YPxzkaXZ9J9YQ1_Lr_6Qj", "snippet": {"videoId": "8A6esi1YcP0", "textDisplay": "\u97e9\u56fd\u8fd0\u52a8\u5458\u7684\u62b1\u6028\u6765\u81ea\u4e8e\u5229\u76ca\u548c\u8150\u8d25\u7684\u4f53\u5236\uff08\u5305\u62ec\u4f46\u4e0d\u9650\u4e8e\u6b64\uff09", "textOriginal": "\u97e9\u56fd\u8fd0\u52a8\u5458\u7684\u62b1\u6028\u6765\u81ea\u4e8e\u5229\u76ca\u548c\u8150\u8d25\u7684\u4f53\u5236\uff08\u5305\u62ec\u4f46\u4e0d\u9650\u4e8e\u6b64\uff09", "parentId": "Ugx3weaBiP0mMJLDy054AaABAg", "authorDisplayName": "\u6211\u7231\u4e2d\u56fd", "authorProfileImageUrl": "https://yt3.ggpht.com/GVpnA4GqMk6N4Wesw7orTrlE7T-9hFwn04DfCjET2BoUiuUG30wAs6caVEtw6hD2rOVKyCIMS7g=s48-c-k-c0x00ffffff-no-rj", "authorChannelUrl": "http://www.youtube.com/channel/UC2PRUkhcf8JbCTe8Fy8wzYA", "authorChannelId": {"value": "UC2PRUkhcf8JbCTe8Fy8wzYA"}, "canRate": true, "viewerRating": "none", "likeCount": 0, "publishedAt": "2022-02-14T05:19:18Z", "updatedAt": "2022-02-14T05:19:18Z"}}]}}, {"kind": "youtube#commentThread", "etag": "TJKbYgMMRbGjRyBcLAUyp7TxeeA", "id": "UgwLEOOvJ1G_9zowSY14AaABAg", "snippet": {"videoId": "8A6esi1YcP0", "topLevelComment": {"kind": "youtube#comment", "etag": "1pSOrQg1WU3sG3pQbjIGYIqbxt4", "id": "UgwLEOOvJ1G_9zowSY14AaABAg", "snippet": {"videoId": "8A6esi1YcP0", "textDisplay": "\u53f0\u6e7e\u76841450\u90fd\u5728\u5fd9\u7740\u9020\u8c23\u62b9\u9ed1\u4e2d\u56fd\uff0c\u800c\u8fd9\u4e9b\u5916\u56fd\u8fd0\u52a8\u5458\u90fd\u5728\u5fd9\u7740\u4eab\u53d7\u5317\u4eac\u51ac\u5b63\u5965\u8fd0\u4f1a\u3002", "textOriginal": "\u53f0\u6e7e\u76841450\u90fd\u5728\u5fd9\u7740\u9020\u8c23\u62b9\u9ed1\u4e2d\u56fd\uff0c\u800c\u8fd9\u4e9b\u5916\u56fd\u8fd0\u52a8\u5458\u90fd\u5728\u5fd9\u7740\u4eab\u53d7\u5317\u4eac\u51ac\u5b63\u5965\u8fd0\u4f1a\u3002", "authorDisplayName": "hljnan", "authorProfileImageUrl": "https://yt3.ggpht.com/CMhGAqpz7grOzCKlUNbzZRefskjqiK0w6sx6FpjmzppPGg6Nh3K3LeH_SORRs-WauQY36eCvaA=s48-c-k-c0x00ffffff-no-rj", "authorChannelUrl": "http://www.youtube.com/channel/UCWp8eHBSmm8VIqiveAZ82aA", "authorChannelId": {"value": "UCWp8eHBSmm8VIqiveAZ82aA"}, "canRate": true, "viewerRating": "none", "likeCount": 0, "publishedAt": "2022-02-13T23:59:07Z", "updatedAt": "2022-02-13T23:59:07Z"}}, "canReply": true, "totalReplyCount": 4, "isPublic": true}, "replies": {"comments": [{"kind": "youtube#comment", "etag": "V41EVOANTJnEK9AE7uwM3utLvBM", "id": "UgwLEOOvJ1G_9zowSY14AaABAg.9YPSwE5EuPt9YUv3dOCsOp", "snippet": {"videoId": "8A6esi1YcP0", "textDisplay": "@\u7fd2\u8fd1\u5e73 \u8fd8\u6709\u4f60\u77e5\u9053\u4ec0\u4e48\u53eb\u73bb\u7483\u5fc3\u5417\uff1f\u63d0\u5230\u5317\u4eac\u51ac\u5b63\u5965\u8fd0\u4f1a\u5c31\u96be\u53d7\uff0c\u8fd9\u5c31\u53eb\u73bb\u7483\u5fc3\uff0c\u4f60\u662f\u4e0d\u662f\u6ca1\u770b\uff1f", "textOriginal": "@\u7fd2\u8fd1\u5e73 \u8fd8\u6709\u4f60\u77e5\u9053\u4ec0\u4e48\u53eb\u73bb\u7483\u5fc3\u5417\uff1f\u63d0\u5230\u5317\u4eac\u51ac\u5b63\u5965\u8fd0\u4f1a\u5c31\u96be\u53d7\uff0c\u8fd9\u5c31\u53eb\u73bb\u7483\u5fc3\uff0c\u4f60\u662f\u4e0d\u662f\u6ca1\u770b\uff1f", "parentId": "UgwLEOOvJ1G_9zowSY14AaABAg", "authorDisplayName": "hljnan", "authorProfileImageUrl": "https://yt3.ggpht.com/CMhGAqpz7grOzCKlUNbzZRefskjqiK0w6sx6FpjmzppPGg6Nh3K3LeH_SORRs-WauQY36eCvaA=s48-c-k-c0x00ffffff-no-rj", "authorChannelUrl": "http://www.youtube.com/channel/UCWp8eHBSmm8VIqiveAZ82aA", "authorChannelId": {"value": "UCWp8eHBSmm8VIqiveAZ82aA"}, "canRate": true, "viewerRating": "none", "likeCount": 0, "publishedAt": "2022-02-16T02:49:52Z", "updatedAt": "2022-02-16T02:49:52Z"}}, {"kind": "youtube#comment", "etag": "bmrWuqUOv3uomSxSnbuZOnlHuLg", "id": "UgwLEOOvJ1G_9zowSY14AaABAg.9YPSwE5EuPt9YUuoubGeK9", "snippet": {"videoId": "8A6esi1YcP0", "textDisplay": "@\u7fd2\u8fd1\u5e73 \u65e5\u672c\u6d17\u6d74\u548c\u4e2d\u570b\u8fd9\u662f\u4e2d\u56fd\u4e1c\u5317\u7684\u4e09\u7ebf\u57ce\u5e02\uff0c\u628a\u4f60\u4e86\u89e3\u4e00\u4e0b\u4e95\u5916\u7684\u4e16\u754c\uff0c\u6771\u5317\u6d17\u6d74\u6587\u5316\uff0c\u6771\u5317\u7f8e\u5973\u89aa\u8eab\u7d93\u6b77\uff0c\u50be\u60c5\u8b1b\u89e3\u3002<a href=\"https://youtu.be/M-YXnaSgMSk\">https://youtu.be/M-YXnaSgMSk</a>", "textOriginal": "@\u7fd2\u8fd1\u5e73 \u65e5\u672c\u6d17\u6d74\u548c\u4e2d\u570b\u8fd9\u662f\u4e2d\u56fd\u4e1c\u5317\u7684\u4e09\u7ebf\u57ce\u5e02\uff0c\u628a\u4f60\u4e86\u89e3\u4e00\u4e0b\u4e95\u5916\u7684\u4e16\u754c\uff0c\u6771\u5317\u6d17\u6d74\u6587\u5316\uff0c\u6771\u5317\u7f8e\u5973\u89aa\u8eab\u7d93\u6b77\uff0c\u50be\u60c5\u8b1b\u89e3\u3002https://youtu.be/M-YXnaSgMSk", "parentId": "UgwLEOOvJ1G_9zowSY14AaABAg", "authorDisplayName": "hljnan", "authorProfileImageUrl": "https://yt3.ggpht.com/CMhGAqpz7grOzCKlUNbzZRefskjqiK0w6sx6FpjmzppPGg6Nh3K3LeH_SORRs-WauQY36eCvaA=s48-c-k-c0x00ffffff-no-rj", "authorChannelUrl": "http://www.youtube.com/channel/UCWp8eHBSmm8VIqiveAZ82aA", "authorChannelId": {"value": "UCWp8eHBSmm8VIqiveAZ82aA"}, "canRate": true, "viewerRating": "none", "likeCount": 0, "publishedAt": "2022-02-16T02:47:44Z", "updatedAt": "2022-02-16T02:47:44Z"}}, {"kind": "youtube#comment", "etag": "AMTngaksLTjfuHT2V3Qu83U22IQ", "id": "UgwLEOOvJ1G_9zowSY14AaABAg.9YPSwE5EuPt9YUuasxwbqV", "snippet": {"videoId": "8A6esi1YcP0", "textDisplay": "@\u7fd2\u8fd1\u5e73 \u90a3\u4e48\u7f8e\u56fd\u8fd9\u4e2a\u4f60\u770b\u5982\u4f55\uff1f\u770b\u770b\u4f60\u5bf9\u62cd\u6444\u8005\u7684\u5206\u8fa8\u80fd\u529b\u5982\u4f55\u3002\u70ba\u4ec0\u9ebc\u81ea\u7531\u6c11\u4e3b\u7684\u7f8e\u570b\u6bd4\u53f0\u7063\u9084\u7aae\uff0c\u770b\u770b\u8cbb\u57ce\u50f5\u5c38\u4e00\u689d\u8857\uff0c\u582a\u6bd4\u53f0\u88ab\u7684\u3002\u3002\u3002<a href=\"https://youtu.be/24mZS1TYZ8w\">https://youtu.be/24mZS1TYZ8w</a>", "textOriginal": "@\u7fd2\u8fd1\u5e73 \u90a3\u4e48\u7f8e\u56fd\u8fd9\u4e2a\u4f60\u770b\u5982\u4f55\uff1f\u770b\u770b\u4f60\u5bf9\u62cd\u6444\u8005\u7684\u5206\u8fa8\u80fd\u529b\u5982\u4f55\u3002\u70ba\u4ec0\u9ebc\u81ea\u7531\u6c11\u4e3b\u7684\u7f8e\u570b\u6bd4\u53f0\u7063\u9084\u7aae\uff0c\u770b\u770b\u8cbb\u57ce\u50f5\u5c38\u4e00\u689d\u8857\uff0c\u582a\u6bd4\u53f0\u88ab\u7684\u3002\u3002\u3002https://youtu.be/24mZS1TYZ8w", "parentId": "UgwLEOOvJ1G_9zowSY14AaABAg", "authorDisplayName": "hljnan", "authorProfileImageUrl": "https://yt3.ggpht.com/CMhGAqpz7grOzCKlUNbzZRefskjqiK0w6sx6FpjmzppPGg6Nh3K3LeH_SORRs-WauQY36eCvaA=s48-c-k-c0x00ffffff-no-rj", "authorChannelUrl": "http://www.youtube.com/channel/UCWp8eHBSmm8VIqiveAZ82aA", "authorChannelId": {"value": "UCWp8eHBSmm8VIqiveAZ82aA"}, "canRate": true, "viewerRating": "none", "likeCount": 0, "publishedAt": "2022-02-16T02:45:49Z", "updatedAt": "2022-02-16T02:45:49Z"}}, {"kind": "youtube#comment", "etag": "d0-x_JymtffCIlr1Y0qZYDQxChI", "id": "UgwLEOOvJ1G_9zowSY14AaABAg.9YPSwE5EuPt9YUidP4yNKO", "snippet": {"videoId": "8A6esi1YcP0", "textDisplay": "\u662f\u7684\u82ac\u5170\u6c34\u5e18\u6d1e\u4f4f\u8d77\u6765\u771f\u4e0d\u9519", "textOriginal": "\u662f\u7684\u82ac\u5170\u6c34\u5e18\u6d1e\u4f4f\u8d77\u6765\u771f\u4e0d\u9519", "parentId": "UgwLEOOvJ1G_9zowSY14AaABAg", "authorDisplayName": "\u7fd2\u8fd1\u5e73", "authorProfileImageUrl": "https://yt3.ggpht.com/ytc/AKedOLSu87WFBKKjg0aSdbHnhwGKpgACy_iVs8HU0MpGTQ=s48-c-k-c0x00ffffff-no-rj", "authorChannelUrl": "http://www.youtube.com/channel/UCccK8EPC8CV7O-pbSpEjt8Q", "authorChannelId": {"value": "UCccK8EPC8CV7O-pbSpEjt8Q"}, "canRate": true, "viewerRating": "none", "likeCount": 0, "publishedAt": "2022-02-16T01:01:18Z", "updatedAt": "2022-02-16T01:01:18Z"}}]}}, {"kind": "youtube#commentThread", "etag": "dkhN4IPA7b8Camvc1NUk1jWWqIs", "id": "UgyLmaWq_W12LPdYls94AaABAg", "snippet": {"videoId": "8A6esi1YcP0", "topLevelComment": {"kind": "youtube#comment", "etag": "0qb-XdkW5F2Ara2A5oM15kxHkPo", "id": "UgyLmaWq_W12LPdYls94AaABAg", "snippet": {"videoId": "8A6esi1YcP0", "textDisplay": "\u56e0\u70ba\u53ea\u6709\u5967\u904b\u6751\u548cBBC\u8aaa\u7684\u4e0d\u4e00\u6a23\uff0c\u5176\u4ed6\u5730\u65b9\u5927\u591a\u6578BBC\u5831\u9053\u7684\u90fd\u5f88\u771f\u5be6\u3002", "textOriginal": "\u56e0\u70ba\u53ea\u6709\u5967\u904b\u6751\u548cBBC\u8aaa\u7684\u4e0d\u4e00\u6a23\uff0c\u5176\u4ed6\u5730\u65b9\u5927\u591a\u6578BBC\u5831\u9053\u7684\u90fd\u5f88\u771f\u5be6\u3002", "authorDisplayName": "Pola", "authorProfileImageUrl": "https://yt3.ggpht.com/ytc/AKedOLTmGyprH7F6wWj5YFdXHDz4-POx4-MKBjkPuQ-ycg=s48-c-k-c0x00ffffff-no-rj", "authorChannelUrl": "http://www.youtube.com/channel/UCINs6J5bf9Ng4kX88tDCy-A", "authorChannelId": {"value": "UCINs6J5bf9Ng4kX88tDCy-A"}, "canRate": true, "viewerRating": "none", "likeCount": 0, "publishedAt": "2022-02-13T16:23:56Z", "updatedAt": "2022-02-13T16:23:56Z"}}, "canReply": true, "totalReplyCount": 1, "isPublic": true}, "replies": {"comments": [{"kind": "youtube#comment", "etag": "2WqlGppzKjotw8kJ1z_GVYaIKLY", "id": "UgyLmaWq_W12LPdYls94AaABAg.9YOdqLAoffO9YOfROSCWW_", "snippet": {"videoId": "8A6esi1YcP0", "textDisplay": "\u5982\u679c\u7ec6\u5fc3\u7684\u8bdd\uff0c\u4f60\u53ef\u4ee5\u53d1\u73b0\uff0cBBC\u5f88\u771f\u5b9e\u62a5\u9053\u7684\u5176\u4ed6\u5730\u65b9 \u51e0\u4e4e\u4e0d\u5305\u62ec\u4e2d\u56fd\u3002", "textOriginal": "\u5982\u679c\u7ec6\u5fc3\u7684\u8bdd\uff0c\u4f60\u53ef\u4ee5\u53d1\u73b0\uff0cBBC\u5f88\u771f\u5b9e\u62a5\u9053\u7684\u5176\u4ed6\u5730\u65b9 \u51e0\u4e4e\u4e0d\u5305\u62ec\u4e2d\u56fd\u3002", "parentId": "UgyLmaWq_W12LPdYls94AaABAg", "authorDisplayName": "\u6211\u7231\u4e2d\u56fd", "authorProfileImageUrl": "https://yt3.ggpht.com/GVpnA4GqMk6N4Wesw7orTrlE7T-9hFwn04DfCjET2BoUiuUG30wAs6caVEtw6hD2rOVKyCIMS7g=s48-c-k-c0x00ffffff-no-rj", "authorChannelUrl": "http://www.youtube.com/channel/UC2PRUkhcf8JbCTe8Fy8wzYA", "authorChannelId": {"value": "UC2PRUkhcf8JbCTe8Fy8wzYA"}, "canRate": true, "viewerRating": "none", "likeCount": 0, "publishedAt": "2022-02-13T16:37:52Z", "updatedAt": "2022-02-13T16:37:52Z"}}]}}, {"kind": "youtube#commentThread", "etag": "LX_bsk59-Rfo9m0UGbILUA3OlSc", "id": "UgwVcJjEwBT4aUV75r54AaABAg", "snippet": {"videoId": "8A6esi1YcP0", "topLevelComment": {"kind": "youtube#comment", "etag": "Cm6tr-xdZrJCmxywurVumh0GNck", "id": "UgwVcJjEwBT4aUV75r54AaABAg", "snippet": {"videoId": "8A6esi1YcP0", "textDisplay": "\u4f60\u8fd9\u4e48\u7ed9\u6211\u9001\u6211\u4e5f\u4e50\u7684\u5408\u4e0d\u62e2\u817f\uff01\u770b\u662f\u4ece\u4e70\u5355\u8005\u7684\u89d2\u5ea6\u8fd8\u662f\u6536\u793c\u7269\u7684\u89d2\u5ea6\u770b\u8fd9\u4e2a\u4e8b\u4e86\uff01", "textOriginal": "\u4f60\u8fd9\u4e48\u7ed9\u6211\u9001\u6211\u4e5f\u4e50\u7684\u5408\u4e0d\u62e2\u817f\uff01\u770b\u662f\u4ece\u4e70\u5355\u8005\u7684\u89d2\u5ea6\u8fd8\u662f\u6536\u793c\u7269\u7684\u89d2\u5ea6\u770b\u8fd9\u4e2a\u4e8b\u4e86\uff01", "authorDisplayName": "Kerwin", "authorProfileImageUrl": "https://yt3.ggpht.com/ytc/AKedOLQtv1M2Yu9JtniDzc-evrp7MvQEg51RIA2cWwCEqQKC9NHZnrj70eGy-9HFp4jp=s48-c-k-c0x00ffffff-no-rj", "authorChannelUrl": "http://www.youtube.com/channel/UCIx_xmpRxQW4ddYDo-hyqWA", "authorChannelId": {"value": "UCIx_xmpRxQW4ddYDo-hyqWA"}, "canRate": true, "viewerRating": "none", "likeCount": 0, "publishedAt": "2022-02-13T15:46:01Z", "updatedAt": "2022-02-13T15:46:01Z"}}, "canReply": true, "totalReplyCount": 0, "isPublic": true}}, {"kind": "youtube#commentThread", "etag": "zdfCgUFd9sJOleeiZnGvv2XKVUU", "id": "UgzLkdimgKAcoQ1IZ5l4AaABAg", "snippet": {"videoId": "8A6esi1YcP0", "topLevelComment": {"kind": "youtube#comment", "etag": "GipNCwAehFagn_FFIbXEzIURDd0", "id": "UgzLkdimgKAcoQ1IZ5l4AaABAg", "snippet": {"videoId": "8A6esi1YcP0", "textDisplay": "chinese are not allowed to do any type of global social media besides tiktok. Why are they on youtube\ud83e\udd23\ud83e\udd23\ud83e\udd23 shit-qinping is watching on u guys!!!!", "textOriginal": "chinese are not allowed to do any type of global social media besides tiktok. Why are they on youtube\ud83e\udd23\ud83e\udd23\ud83e\udd23 shit-qinping is watching on u guys!!!!", "authorDisplayName": "gonzales p", "authorProfileImageUrl": "https://yt3.ggpht.com/eWtOYn8kCWFrZd4JT7zALLXi2kYSKNGKQ6kW8TR2IiTaluFb8sgdnRvMed74-nkveQQJFq_6vQ=s48-c-k-c0x00ffffff-no-rj", "authorChannelUrl": "http://www.youtube.com/channel/UCfsCQtmjyVl3Sf7klpeEbQw", "authorChannelId": {"value": "UCfsCQtmjyVl3Sf7klpeEbQw"}, "canRate": true, "viewerRating": "none", "likeCount": 0, "publishedAt": "2022-02-12T16:30:39Z", "updatedAt": "2022-02-12T16:31:54Z"}}, "canReply": true, "totalReplyCount": 0, "isPublic": true}}, {"kind": "youtube#commentThread", "etag": "wBkvkT960UQWdgOyqn0QUXM9BdU", "id": "UgxQ-JIMvkytVK9PfgF4AaABAg", "snippet": {"videoId": "8A6esi1YcP0", "topLevelComment": {"kind": "youtube#comment", "etag": "mTJz6xQFvJaO9qNLie8PlxqIZwI", "id": "UgxQ-JIMvkytVK9PfgF4AaABAg", "snippet": {"videoId": "8A6esi1YcP0", "textDisplay": "\u8d5e\u6210\u7ef4\u543e\u5c14\u65cf\u4eba\u72ec\u7acb,\u6b22\u8fce\u554a", "textOriginal": "\u8d5e\u6210\u7ef4\u543e\u5c14\u65cf\u4eba\u72ec\u7acb,\u6b22\u8fce\u554a", "authorDisplayName": "gonzales p", "authorProfileImageUrl": "https://yt3.ggpht.com/eWtOYn8kCWFrZd4JT7zALLXi2kYSKNGKQ6kW8TR2IiTaluFb8sgdnRvMed74-nkveQQJFq_6vQ=s48-c-k-c0x00ffffff-no-rj", "authorChannelUrl": "http://www.youtube.com/channel/UCfsCQtmjyVl3Sf7klpeEbQw", "authorChannelId": {"value": "UCfsCQtmjyVl3Sf7klpeEbQw"}, "canRate": true, "viewerRating": "none", "likeCount": 0, "publishedAt": "2022-02-12T16:27:37Z", "updatedAt": "2022-02-12T16:27:37Z"}}, "canReply": true, "totalReplyCount": 0, "isPublic": true}}, {"kind": "youtube#commentThread", "etag": "5UUb_35NdPAT_W5e8pMQo_1KWzc", "id": "UgxkgTi4fCagN1p1wcZ4AaABAg", "snippet": {"videoId": "8A6esi1YcP0", "topLevelComment": {"kind": "youtube#comment", "etag": "IF9QCm5xoTetn2rQ5fsk29MQNMk", "id": "UgxkgTi4fCagN1p1wcZ4AaABAg", "snippet": {"videoId": "8A6esi1YcP0", "textDisplay": "\u6211\u4e5f\u7231\u4e2d\u56fd\u7231\u4e16\u754c\u4eba\u6c11\u3001\u6211\u4e0d\u4f1a\u7231\u4e2d\u5171\u72ec\u88c1\u4e13\u5236\uff0c\u4e2d\u5171\u51ac\u5965\u72ec\u88c1\u4e13\u5236\u7684\u805a\u4f1a", "textOriginal": "\u6211\u4e5f\u7231\u4e2d\u56fd\u7231\u4e16\u754c\u4eba\u6c11\u3001\u6211\u4e0d\u4f1a\u7231\u4e2d\u5171\u72ec\u88c1\u4e13\u5236\uff0c\u4e2d\u5171\u51ac\u5965\u72ec\u88c1\u4e13\u5236\u7684\u805a\u4f1a", "authorDisplayName": "\u5ba1\u5224\u4e2d\u5171", "authorProfileImageUrl": "https://yt3.ggpht.com/_Wa05kDi340-A2WB2_Bf4KN4xaKRh9CmfF6P8016K8XbneG10LqKPOl7gCHhTfZjFe3LX9iCel4=s48-c-k-c0x00ffffff-no-rj", "authorChannelUrl": "http://www.youtube.com/channel/UCSzNPvatcybz4AfyOKRNWlg", "authorChannelId": {"value": "UCSzNPvatcybz4AfyOKRNWlg"}, "canRate": true, "viewerRating": "none", "likeCount": 0, "publishedAt": "2022-02-12T11:58:43Z", "updatedAt": "2022-02-12T11:58:43Z"}}, "canReply": true, "totalReplyCount": 2, "isPublic": true}, "replies": {"comments": [{"kind": "youtube#comment", "etag": "F3DcRfkfivgKkeOfV9RDcdrH0gE", "id": "UgxkgTi4fCagN1p1wcZ4AaABAg.9YLagzdXanR9YNYxuZsqa9", "snippet": {"videoId": "8A6esi1YcP0", "textDisplay": "@\u6211\u7231\u4e2d\u56fd \u4e2d\u5171\u662f\u975e\u6cd5\u653f\u6743\u6211\u4ece\u6765\u6ca1\u6295\u8fc7\u7968\uff0c\u6211\u662f\u5927\u9646\u7684\u4e2d\u56fd\u4eba\u4f60\u9a97\u4e0d\u4e86\u6211\u597d\u5427\uff0c\u4e2d\u534e\u6c11\u56fd\u5728\u53f0\u6e7e\u662f\u6c11\u4e3b\u5baa\u653f\u56fd\u5bb6\u81f3\u4eca111\u5e74\u4eba\u5747\u6536\u5165\u6bd4\u4e2d\u56fd\u5927\u9646\u9ad8\u51fa\u4e24\u500d\uff0c\u5168\u6c11\u533b\u4fdd\u770b\u75c5\u53ea\u82b1\u6302\u53f7\u8d39\uff0c\u8bf4\u771f\u8bdd\u4e0d\u4f1a\u6050\u60e7\uff0c\u6709\u6295\u7968\u6743\uff0c", "textOriginal": "@\u6211\u7231\u4e2d\u56fd \u4e2d\u5171\u662f\u975e\u6cd5\u653f\u6743\u6211\u4ece\u6765\u6ca1\u6295\u8fc7\u7968\uff0c\u6211\u662f\u5927\u9646\u7684\u4e2d\u56fd\u4eba\u4f60\u9a97\u4e0d\u4e86\u6211\u597d\u5427\uff0c\u4e2d\u534e\u6c11\u56fd\u5728\u53f0\u6e7e\u662f\u6c11\u4e3b\u5baa\u653f\u56fd\u5bb6\u81f3\u4eca111\u5e74\u4eba\u5747\u6536\u5165\u6bd4\u4e2d\u56fd\u5927\u9646\u9ad8\u51fa\u4e24\u500d\uff0c\u5168\u6c11\u533b\u4fdd\u770b\u75c5\u53ea\u82b1\u6302\u53f7\u8d39\uff0c\u8bf4\u771f\u8bdd\u4e0d\u4f1a\u6050\u60e7\uff0c\u6709\u6295\u7968\u6743\uff0c", "parentId": "UgxkgTi4fCagN1p1wcZ4AaABAg", "authorDisplayName": "\u5ba1\u5224\u4e2d\u5171", "authorProfileImageUrl": "https://yt3.ggpht.com/_Wa05kDi340-A2WB2_Bf4KN4xaKRh9CmfF6P8016K8XbneG10LqKPOl7gCHhTfZjFe3LX9iCel4=s48-c-k-c0x00ffffff-no-rj", "authorChannelUrl": "http://www.youtube.com/channel/UCSzNPvatcybz4AfyOKRNWlg", "authorChannelId": {"value": "UCSzNPvatcybz4AfyOKRNWlg"}, "canRate": true, "viewerRating": "none", "likeCount": 0, "publishedAt": "2022-02-13T06:13:18Z", "updatedAt": "2022-02-13T06:13:18Z"}}, {"kind": "youtube#comment", "etag": "c5VkmbUMlkyOb0E8uU5JBQxcIbI", "id": "UgxkgTi4fCagN1p1wcZ4AaABAg.9YLagzdXanR9YLs2vg36Oz", "snippet": {"videoId": "8A6esi1YcP0", "textDisplay": "\u72ec\u88c1\u662f\u5386\u53f2\uff0c\u662f\u848b\u4ecb\u77f3\u90a3\u4e00\u5957\u3002\u5171\u4ea7\u515a\u7684\u539f\u5219\u59cb\u7ec8\u662f\u4ee3\u8868\u4eba\u6c11\u7684\u5229\u76ca\u3002 \u53cd\u8fc7\u6765\u8bf4\uff0c\u5982\u679c\u5171\u4ea7\u515a\u72ec\u88c1\uff0c\u5c31\u4e0d\u4f1a\u6709\u5982\u4eca\u7684\u76db\u4e16\u4e2d\u534e\u3002\u4e2d\u56fd\u4eba\u6c11\u5df2\u7ecf\u7ad9\u8d77\u6765\u4e86\uff01", "textOriginal": "\u72ec\u88c1\u662f\u5386\u53f2\uff0c\u662f\u848b\u4ecb\u77f3\u90a3\u4e00\u5957\u3002\u5171\u4ea7\u515a\u7684\u539f\u5219\u59cb\u7ec8\u662f\u4ee3\u8868\u4eba\u6c11\u7684\u5229\u76ca\u3002 \u53cd\u8fc7\u6765\u8bf4\uff0c\u5982\u679c\u5171\u4ea7\u515a\u72ec\u88c1\uff0c\u5c31\u4e0d\u4f1a\u6709\u5982\u4eca\u7684\u76db\u4e16\u4e2d\u534e\u3002\u4e2d\u56fd\u4eba\u6c11\u5df2\u7ecf\u7ad9\u8d77\u6765\u4e86\uff01", "parentId": "UgxkgTi4fCagN1p1wcZ4AaABAg", "authorDisplayName": "\u6211\u7231\u4e2d\u56fd", "authorProfileImageUrl": "https://yt3.ggpht.com/GVpnA4GqMk6N4Wesw7orTrlE7T-9hFwn04DfCjET2BoUiuUG30wAs6caVEtw6hD2rOVKyCIMS7g=s48-c-k-c0x00ffffff-no-rj", "authorChannelUrl": "http://www.youtube.com/channel/UC2PRUkhcf8JbCTe8Fy8wzYA", "authorChannelId": {"value": "UC2PRUkhcf8JbCTe8Fy8wzYA"}, "canRate": true, "viewerRating": "none", "likeCount": 0, "publishedAt": "2022-02-12T14:30:24Z", "updatedAt": "2022-02-12T14:30:24Z"}}]}}, {"kind": "youtube#commentThread", "etag": "0Y6F8jT06pSM2jyoPs82UTLtE1c", "id": "UgzVteYrhAz5MUEUcU54AaABAg", "snippet": {"videoId": "8A6esi1YcP0", "topLevelComment": {"kind": "youtube#comment", "etag": "l_bYcaE-KbO5mf73RylyQi-DHG0", "id": "UgzVteYrhAz5MUEUcU54AaABAg", "snippet": {"videoId": "8A6esi1YcP0", "textDisplay": "\u600e\u4e48\u611f\u89c9\u770b\u51fa\u4e86\u4e00\u7fa4\u8fd0\u52a8\u5458\u5728\u5168\u7403\u75ab\u60c5\u4e0b\u53bb\u65c5\u6e38\u7684\u611f\u89c9= =```", "textOriginal": "\u600e\u4e48\u611f\u89c9\u770b\u51fa\u4e86\u4e00\u7fa4\u8fd0\u52a8\u5458\u5728\u5168\u7403\u75ab\u60c5\u4e0b\u53bb\u65c5\u6e38\u7684\u611f\u89c9= =```", "authorDisplayName": "Hansko Lau", "authorProfileImageUrl": "https://yt3.ggpht.com/ytc/AKedOLR7GXS_nNJueiBXtUh2O2nwWiTnAbHRbW7GOg=s48-c-k-c0x00ffffff-no-rj", "authorChannelUrl": "http://www.youtube.com/channel/UCvDDPGtppXdLj4qFTC82mFA", "authorChannelId": {"value": "UCvDDPGtppXdLj4qFTC82mFA"}, "canRate": true, "viewerRating": "none", "likeCount": 1, "publishedAt": "2022-02-11T20:37:29Z", "updatedAt": "2022-02-11T20:37:29Z"}}, "canReply": true, "totalReplyCount": 0, "isPublic": true}}, {"kind": "youtube#commentThread", "etag": "9Hu4_Rtez2dSgaRf9Wc3lZPhtmo", "id": "UgxNkpwWNwPqAgqpB3J4AaABAg", "snippet": {"videoId": "8A6esi1YcP0", "topLevelComment": {"kind": "youtube#comment", "etag": "NqogAoo-n-N3ZcivusWOk7OpDUU", "id": "UgxNkpwWNwPqAgqpB3J4AaABAg", "snippet": {"videoId": "8A6esi1YcP0", "textDisplay": "lol of course it&#39;s different BBC is fake news agency they only report news that praise the west and belittle the east. that&#39;s what they do BBC is one of the UK government agencies that helps with the western propaganda against the east for quite a number of years", "textOriginal": "lol of course it's different BBC is fake news agency they only report news that praise the west and belittle the east. that's what they do BBC is one of the UK government agencies that helps with the western propaganda against the east for quite a number of years", "authorDisplayName": "Pete Lee", "authorProfileImageUrl": "https://yt3.ggpht.com/ytc/AKedOLTIiw6lgoxYrM7podevptoqEUja85ceR8LSOdWCwLw=s48-c-k-c0x00ffffff-no-rj", "authorChannelUrl": "http://www.youtube.com/channel/UCJpEz5wEENEHN35RT-Nt95A", "authorChannelId": {"value": "UCJpEz5wEENEHN35RT-Nt95A"}, "canRate": true, "viewerRating": "none", "likeCount": 0, "publishedAt": "2022-02-11T15:58:02Z", "updatedAt": "2022-02-11T15:58:02Z"}}, "canReply": true, "totalReplyCount": 0, "isPublic": true}}, {"kind": "youtube#commentThread", "etag": "ABJl963C8UyiyinHKInjnSO9uXA", "id": "UgxdMEhm35nsN41nZRR4AaABAg", "snippet": {"videoId": "8A6esi1YcP0", "topLevelComment": {"kind": "youtube#comment", "etag": "-NWpPZXIiPOUjgC8SKbRn-BMJvI", "id": "UgxdMEhm35nsN41nZRR4AaABAg", "snippet": {"videoId": "8A6esi1YcP0", "textDisplay": "bbc\u4e00\u6837\u53ef\u4ee5\u8bf4\uff0c\u8fd9\u662f\u538b\u8feb\u4e8614\u4ebf\u4eba\u6324\u51fa\u6765\u7684\u623f\u95f4\uff0c\u54c8\u54c8\u54c8\u54c8\ud83e\udd23", "textOriginal": "bbc\u4e00\u6837\u53ef\u4ee5\u8bf4\uff0c\u8fd9\u662f\u538b\u8feb\u4e8614\u4ebf\u4eba\u6324\u51fa\u6765\u7684\u623f\u95f4\uff0c\u54c8\u54c8\u54c8\u54c8\ud83e\udd23", "authorDisplayName": "Zhenyu Shen", "authorProfileImageUrl": "https://yt3.ggpht.com/ytc/AKedOLSLvfbNJ3YhYK5ZldQV9SDqssvyr4vDd4Cz-zH063Q=s48-c-k-c0x00ffffff-no-rj", "authorChannelUrl": "http://www.youtube.com/channel/UCsnqmchxVSvY-9f-iNhDphw", "authorChannelId": {"value": "UCsnqmchxVSvY-9f-iNhDphw"}, "canRate": true, "viewerRating": "none", "likeCount": 0, "publishedAt": "2022-02-11T07:21:58Z", "updatedAt": "2022-02-11T07:21:58Z"}}, "canReply": true, "totalReplyCount": 1, "isPublic": true}, "replies": {"comments": [{"kind": "youtube#comment", "etag": "wQYBJMekiddonoPf37nP6sALyyY", "id": "UgxdMEhm35nsN41nZRR4AaABAg.9YIXE6l4Mxt9YJS-g7P79d", "snippet": {"videoId": "8A6esi1YcP0", "textDisplay": "BBC\u7684\u9020\u8c23\u80fd\u529b\u59cb\u7ec8\u6765\u81ea\u4e8e\u50b2\u6162\u548c\u504f\u89c1\uff0c\u4e5f\u59cb\u7ec8\u5ffd\u89c6\u771f\u60f3", "textOriginal": "BBC\u7684\u9020\u8c23\u80fd\u529b\u59cb\u7ec8\u6765\u81ea\u4e8e\u50b2\u6162\u548c\u504f\u89c1\uff0c\u4e5f\u59cb\u7ec8\u5ffd\u89c6\u771f\u60f3", "parentId": "UgxdMEhm35nsN41nZRR4AaABAg", "authorDisplayName": "\u6211\u7231\u4e2d\u56fd", "authorProfileImageUrl": "https://yt3.ggpht.com/GVpnA4GqMk6N4Wesw7orTrlE7T-9hFwn04DfCjET2BoUiuUG30wAs6caVEtw6hD2rOVKyCIMS7g=s48-c-k-c0x00ffffff-no-rj", "authorChannelUrl": "http://www.youtube.com/channel/UC2PRUkhcf8JbCTe8Fy8wzYA", "authorChannelId": {"value": "UC2PRUkhcf8JbCTe8Fy8wzYA"}, "canRate": true, "viewerRating": "none", "likeCount": 0, "publishedAt": "2022-02-11T15:55:33Z", "updatedAt": "2022-02-11T15:55:33Z"}}]}}, {"kind": "youtube#commentThread", "etag": "RfnuNAIYYIqjqT_Lhj6VGeh4QR8", "id": "Ugyn-0NWwvliV6PjaQN4AaABAg", "snippet": {"videoId": "8A6esi1YcP0", "topLevelComment": {"kind": "youtube#comment", "etag": "xAwQsxwXf013MgOAvLfRUt4wAqE", "id": "Ugyn-0NWwvliV6PjaQN4AaABAg", "snippet": {"videoId": "8A6esi1YcP0", "textDisplay": "\u4e2d\u534e\u6c11\u65cf\u6709\u5e95\u7ebf\uff0c\u7ef4\u62a4\u6211\u4eec\u534e\u590f\u6c11\u65cf\u4e0d\u88ab\u6362\u8840\u66ff\u6362\u7684\u5e95\u7ebf\uff0c\u4f46\u662f\u5171\u755c\u515a\u4e3a\u4e86\u77ed\u671f\u7684\u7ecf\u6d4e\u5229\u76ca\u548c\u5176\u81ea\u8eab\u7684\u56fd\u9645\u5408\u6cd5\u6027\uff0c\u62ff\u534e\u590f\u6c11\u65cf\u7684\u8840\u8109\u4f5c\u4e3a\u7b79\u7801\u53bb\u4ea4\u6613\uff0c\u5927\u8086\u5f15\u5165\u9ed1\u4eba\uff0c\u4ece\u5e7c\u513f\u56ed\u9ed1\u5916\u6559\u5f00\u59cb\u6d17\u8111\u6211\u4eec\u7684\u5b69\u5b50\uff0c\u65f6\u4e0d\u65f6\u62ff\u51fa\u4e2d\u534e\u6587\u660e\u548c\u534e\u590f\u6c11\u65cf\u65e0\u5173\u7684\u865a\u65e0\u5386\u53f2\u4e3b\u4e49\uff0c\u6de1\u5316\u534e\u590f\u8840\u7f18\u7ee7\u627f\u7684\u91cd\u8981\u6027\uff0c\u4e3a\u9ed1\u4eba\u9e4a\u5de2\u9e20\u8e1e\uff0c\u67d3\u9ed1\u708e\u9ec4\u5b50\u5b59,\u5360\u636e\u6211\u534e\u590f\u65cf\u8015\u80185000\u5e74\u7684\u552f\u4e00\u56fd\u5ea6\u505a\u94fa\u57ab\u3002\u6211\u4eec\u7684\u6bcf\u4e00\u5bf8\u571f\u5730\u90fd\u7559\u7740\u7956\u5148\u4eec\u7684\u8840\u548c\u6c57\uff0c\u800c\u4e2d\u56fd\u5171\u755c\u515a\u5c31\u8981\u5c06\u8fd9\u4efd\u571f\u5730\u732e\u796d\u7ed9\u975e\u6d32\u6700\u4e00\u4e8b\u65e0\u6210\u7684\u79cd\u65cf\uff0c\u6d41\u8840\u6d41\u6c57\u4e3a\u56fd\u5bb6\u4ed8\u51fa\u751f\u547d\u7684\u5148\u8d24\u82f1\u70c8\u4eec\u5730\u4e0b\u6709\u77e5\uff0c\u8be5\u505a\u548c\u611f\u60f3\uff1f", "textOriginal": "\u4e2d\u534e\u6c11\u65cf\u6709\u5e95\u7ebf\uff0c\u7ef4\u62a4\u6211\u4eec\u534e\u590f\u6c11\u65cf\u4e0d\u88ab\u6362\u8840\u66ff\u6362\u7684\u5e95\u7ebf\uff0c\u4f46\u662f\u5171\u755c\u515a\u4e3a\u4e86\u77ed\u671f\u7684\u7ecf\u6d4e\u5229\u76ca\u548c\u5176\u81ea\u8eab\u7684\u56fd\u9645\u5408\u6cd5\u6027\uff0c\u62ff\u534e\u590f\u6c11\u65cf\u7684\u8840\u8109\u4f5c\u4e3a\u7b79\u7801\u53bb\u4ea4\u6613\uff0c\u5927\u8086\u5f15\u5165\u9ed1\u4eba\uff0c\u4ece\u5e7c\u513f\u56ed\u9ed1\u5916\u6559\u5f00\u59cb\u6d17\u8111\u6211\u4eec\u7684\u5b69\u5b50\uff0c\u65f6\u4e0d\u65f6\u62ff\u51fa\u4e2d\u534e\u6587\u660e\u548c\u534e\u590f\u6c11\u65cf\u65e0\u5173\u7684\u865a\u65e0\u5386\u53f2\u4e3b\u4e49\uff0c\u6de1\u5316\u534e\u590f\u8840\u7f18\u7ee7\u627f\u7684\u91cd\u8981\u6027\uff0c\u4e3a\u9ed1\u4eba\u9e4a\u5de2\u9e20\u8e1e\uff0c\u67d3\u9ed1\u708e\u9ec4\u5b50\u5b59,\u5360\u636e\u6211\u534e\u590f\u65cf\u8015\u80185000\u5e74\u7684\u552f\u4e00\u56fd\u5ea6\u505a\u94fa\u57ab\u3002\u6211\u4eec\u7684\u6bcf\u4e00\u5bf8\u571f\u5730\u90fd\u7559\u7740\u7956\u5148\u4eec\u7684\u8840\u548c\u6c57\uff0c\u800c\u4e2d\u56fd\u5171\u755c\u515a\u5c31\u8981\u5c06\u8fd9\u4efd\u571f\u5730\u732e\u796d\u7ed9\u975e\u6d32\u6700\u4e00\u4e8b\u65e0\u6210\u7684\u79cd\u65cf\uff0c\u6d41\u8840\u6d41\u6c57\u4e3a\u56fd\u5bb6\u4ed8\u51fa\u751f\u547d\u7684\u5148\u8d24\u82f1\u70c8\u4eec\u5730\u4e0b\u6709\u77e5\uff0c\u8be5\u505a\u548c\u611f\u60f3\uff1f", "authorDisplayName": "isme eiger", "authorProfileImageUrl": "https://yt3.ggpht.com/ytc/AKedOLS8rLOdYIsvy9G9ZNrWfWdl8Zxk60WHsFFQtQ=s48-c-k-c0x00ffffff-no-rj", "authorChannelUrl": "http://www.youtube.com/channel/UCdMgENoVw4GREMkYzwjwo_Q", "authorChannelId": {"value": "UCdMgENoVw4GREMkYzwjwo_Q"}, "canRate": true, "viewerRating": "none", "likeCount": 0, "publishedAt": "2022-02-11T06:46:36Z", "updatedAt": "2022-02-11T06:46:36Z"}}, "canReply": true, "totalReplyCount": 0, "isPublic": true}}, {"kind": "youtube#commentThread", "etag": "pxtKzFiUMWQdN55EhdCx4BMZWfs", "id": "Ugyyl-nccSYRyoVdw4p4AaABAg", "snippet": {"videoId": "8A6esi1YcP0", "topLevelComment": {"kind": "youtube#comment", "etag": "KLXcCiKnyK6jfHhGK86BjdQ0OSk", "id": "Ugyyl-nccSYRyoVdw4p4AaABAg", "snippet": {"videoId": "8A6esi1YcP0", "textDisplay": "\u70ba\u6240\u6709\u51ac\u5967\u904b\u52d5\u54e1\u52a0\u6cb9\ud83d\udcaa\u52a0\u6cb9\ud83d\udcaa\u52a0\u6cb9\ud83d\udcaa", "textOriginal": "\u70ba\u6240\u6709\u51ac\u5967\u904b\u52d5\u54e1\u52a0\u6cb9\ud83d\udcaa\u52a0\u6cb9\ud83d\udcaa\u52a0\u6cb9\ud83d\udcaa", "authorDisplayName": "Tsang Kwai Ting", "authorProfileImageUrl": "https://yt3.ggpht.com/ytc/AKedOLSdWUckP0rtPmIIayP9MkDEDiGXm7gWXMYASQ=s48-c-k-c0x00ffffff-no-rj", "authorChannelUrl": "http://www.youtube.com/channel/UCaxVxndqvOIa0QWxiw-Pz_w", "authorChannelId": {"value": "UCaxVxndqvOIa0QWxiw-Pz_w"}, "canRate": true, "viewerRating": "none", "likeCount": 0, "publishedAt": "2022-02-10T17:43:03Z", "updatedAt": "2022-02-10T17:43:03Z"}}, "canReply": true, "totalReplyCount": 0, "isPublic": true}}, {"kind": "youtube#commentThread", "etag": "VoJGeHLZOyGH9MX3d_mzPzi01S4", "id": "UgwoivtnL6qiNmG-YjN4AaABAg", "snippet": {"videoId": "8A6esi1YcP0", "topLevelComment": {"kind": "youtube#comment", "etag": "iaQ6rkxW4yTgBBrF_iVTV-t1pek", "id": "UgwoivtnL6qiNmG-YjN4AaABAg", "snippet": {"videoId": "8A6esi1YcP0", "textDisplay": "\u590f\u5b63\u5965\u8fd0\u4f1a\u7adf\u7136\u6bd4\u51ac\u5b63\u5965\u8fd0\u4f1a\u8ba9\u4eba\u611f\u5230\u66f4\u51b7\uff01", "textOriginal": "\u590f\u5b63\u5965\u8fd0\u4f1a\u7adf\u7136\u6bd4\u51ac\u5b63\u5965\u8fd0\u4f1a\u8ba9\u4eba\u611f\u5230\u66f4\u51b7\uff01", "authorDisplayName": "John Xu", "authorProfileImageUrl": "https://yt3.ggpht.com/GL_2LWXLzKDUBIJemmgsnTA5dx0NOsnNCMXUeozxGokQhMNF-Jb3uDdV-pL_XU9Zb6fziYPkVw=s48-c-k-c0x00ffffff-no-rj", "authorChannelUrl": "http://www.youtube.com/channel/UC46K03371MLAdZw8aWdsUUA", "authorChannelId": {"value": "UC46K03371MLAdZw8aWdsUUA"}, "canRate": true, "viewerRating": "none", "likeCount": 0, "publishedAt": "2022-02-10T13:55:12Z", "updatedAt": "2022-02-10T13:55:12Z"}}, "canReply": true, "totalReplyCount": 0, "isPublic": true}}, {"kind": "youtube#commentThread", "etag": "g5DIscItggtbU9-uTXklxDWzsSA", "id": "UgykycfLWkr8CU2VWdl4AaABAg", "snippet": {"videoId": "8A6esi1YcP0", "topLevelComment": {"kind": "youtube#comment", "etag": "5vf_YjqNn342sPLKr8CdR3mivtk", "id": "UgykycfLWkr8CU2VWdl4AaABAg", "snippet": {"videoId": "8A6esi1YcP0", "textDisplay": "<a href=\"https://youtu.be/RboVds70H4Y\">https://youtu.be/RboVds70H4Y</a>", "textOriginal": "https://youtu.be/RboVds70H4Y", "authorDisplayName": "water Mu", "authorProfileImageUrl": "https://yt3.ggpht.com/ytc/AKedOLSqF9aOzmhVlNrCBC30Gt471JuVLoTRbt7Ja_wFEQ=s48-c-k-c0x00ffffff-no-rj", "authorChannelUrl": "http://www.youtube.com/channel/UC-WEYMEWprshXBy3bdfymAA", "authorChannelId": {"value": "UC-WEYMEWprshXBy3bdfymAA"}, "canRate": true, "viewerRating": "none", "likeCount": 0, "publishedAt": "2022-02-09T20:55:08Z", "updatedAt": "2022-02-09T20:55:08Z"}}, "canReply": true, "totalReplyCount": 0, "isPublic": true}}, {"kind": "youtube#commentThread", "etag": "hn7txPwbDIjrzeJ_8PQZ4wU8O4U", "id": "UgzEPZQ5jhIPiS9dMPB4AaABAg", "snippet": {"videoId": "8A6esi1YcP0", "topLevelComment": {"kind": "youtube#comment", "etag": "eOvOQfX0niv-QqQQ_jXz1HOqPbU", "id": "UgzEPZQ5jhIPiS9dMPB4AaABAg", "snippet": {"videoId": "8A6esi1YcP0", "textDisplay": "\u5982\u679c\u662f\u88abDQ\u7684\u9078\u624b\u5c31\u4e0d\u6703\u9019\u6a23\u6253\u5361\u4e86", "textOriginal": "\u5982\u679c\u662f\u88abDQ\u7684\u9078\u624b\u5c31\u4e0d\u6703\u9019\u6a23\u6253\u5361\u4e86", "authorDisplayName": "Fan Fan", "authorProfileImageUrl": "https://yt3.ggpht.com/ytc/AKedOLR7DSbB-PNV-pgZmZySm__3RYC8zyEYnnD5ow=s48-c-k-c0x00ffffff-no-rj", "authorChannelUrl": "http://www.youtube.com/channel/UCJhzCZZfA8NiEIYHx5M5R4Q", "authorChannelId": {"value": "UCJhzCZZfA8NiEIYHx5M5R4Q"}, "canRate": true, "viewerRating": "none", "likeCount": 0, "publishedAt": "2022-02-09T16:37:16Z", "updatedAt": "2022-02-09T16:37:16Z"}}, "canReply": true, "totalReplyCount": 0, "isPublic": true}}, {"kind": "youtube#commentThread", "etag": "GxJ2JFxJHXiyEWhGhCpvEvymJGc", "id": "UgzTYF8TNCC9z_VQJfd4AaABAg", "snippet": {"videoId": "8A6esi1YcP0", "topLevelComment": {"kind": "youtube#comment", "etag": "ssgrQ2-9q14m3kNJmeqK1oG3Dy4", "id": "UgzTYF8TNCC9z_VQJfd4AaABAg", "snippet": {"videoId": "8A6esi1YcP0", "textDisplay": "\u771f\u662f\u4e8b\u5b9e\u5b9e\u4e8b\u662f\uff01 \u4e0d\u5bb9\u5047\u8c2c\u52a0\u62b5\u5236 \uff01", "textOriginal": "\u771f\u662f\u4e8b\u5b9e\u5b9e\u4e8b\u662f\uff01 \u4e0d\u5bb9\u5047\u8c2c\u52a0\u62b5\u5236 \uff01", "authorDisplayName": "Sung Katherine", "authorProfileImageUrl": "https://yt3.ggpht.com/ytc/AKedOLRBZoV5DWgcsXZgOlC8qrLXRbSeJnDAmF2s-bhYuA=s48-c-k-c0x00ffffff-no-rj", "authorChannelUrl": "http://www.youtube.com/channel/UC7kDTaHoCFBOwR0hW9bcinQ", "authorChannelId": {"value": "UC7kDTaHoCFBOwR0hW9bcinQ"}, "canRate": true, "viewerRating": "none", "likeCount": 0, "publishedAt": "2022-02-09T09:49:48Z", "updatedAt": "2022-02-09T09:49:48Z"}}, "canReply": true, "totalReplyCount": 0, "isPublic": true}}]}